setup.py
GuessGames/HigherLowerGame.py
GuessGames/__init__.py
GuessGames.egg-info/PKG-INFO
GuessGames.egg-info/SOURCES.txt
GuessGames.egg-info/dependency_links.txt
GuessGames.egg-info/top_level.txt